pykka_injector
