Metadata-Version: 1.1
Name: pykka-injector
Version: 0.1.1
Summary: Pykka (actor model implementation) and Injector (dependency injection framework) integration module
Home-page: http://github.com/jstasiak/pykka-injector
Author: Jakub Stasiak
Author-email: jakub@stasiak.at
License: MIT
Download-URL: http://pypi.python.org/pypi/pykka-injector
Keywords: Dependency Injection,Injector,Pykka
Platform: any
